verniersl/__main__.py
verniersl/ble.py
vernier_lsl-0.2.1.dist-info/METADATA
vernier_lsl-0.2.1.dist-info/WHEEL
vernier_lsl-0.2.1.dist-info/entry_points.txt
vernier_lsl-0.2.1.dist-info/top_level.txt
vernier_lsl-0.2.1.dist-info/RECORD
