Metadata-Version: 2.1
Name: vernier-lsl
Version: 0.2.1
Summary: Toolbox to receive godirect data and send as LSL streams.
Home-page: https://github.com/translationalneurosurgery/app-vernier.git
Author: Robert Guggenberger
Author-email: robert.guggenberger@uni-tuebingen.de
License: MIT
Download-URL: https://github.com/translationalneurosurgery/app-vernier.git
Platform: UNKNOWN
Classifier: Development Status :: 4 - Beta
Classifier: Environment :: Console
Classifier: Intended Audience :: Developers
Classifier: Intended Audience :: Education
Classifier: Intended Audience :: Healthcare Industry
Classifier: Intended Audience :: Science/Research
Classifier: Intended Audience :: Information Technology
Classifier: License :: OSI Approved :: MIT License
Classifier: Operating System :: OS Independent
Classifier: Programming Language :: Python
Classifier: Programming Language :: Python :: 3
Classifier: Topic :: Scientific/Engineering :: Human Machine Interfaces
Classifier: Topic :: Scientific/Engineering :: Medical Science Apps.
Classifier: Topic :: Software Development :: Libraries
Requires-Dist: godirect
Requires-Dist: pylsl
Requires-Dist: vernierpygatt
